pybmd/__init__.py
pybmd/_init_bmd.py
pybmd/_wrapper_base.py
pybmd/color_group.py
pybmd/error.py
pybmd/export_type.py
pybmd/folder.py
pybmd/fusion.py
pybmd/fusion_comp.py
pybmd/gallery.py
pybmd/gallery_still.py
pybmd/gallery_still_album.py
pybmd/graph.py
pybmd/logging_config.py
pybmd/media_pool.py
pybmd/media_pool_item.py
pybmd/media_storage.py
pybmd/project.py
pybmd/project_manager.py
pybmd/resolve.py
pybmd/settings.py
pybmd/timeline.py
pybmd/timeline_item.py
pybmd/toolkits.py
pybmd/ui_dispather.py
pybmd/ui_manager.py
pybmd-2026.0.1.dist-info/METADATA
pybmd-2026.0.1.dist-info/WHEEL
pybmd-2026.0.1.dist-info/licenses/LICENSE
pybmd-2026.0.1.dist-info/RECORD
