Metadata-Version: 2.4
Name: pybmd
Version: 2026.0.1
Summary: python library for Davinci Resolve(Repack)
Project-URL: Homepage, https://github.com/WheheoHu/pybmd
Project-URL: Repository, https://github.com/WheheoHu/pybmd
Author-email: wheheo <wheheohu@outlook.com>
License: LGPL-3.0-or-later
License-File: LICENSE
Classifier: License :: OSI Approved :: GNU Lesser General Public License v3 or later (LGPLv3+)
Classifier: Operating System :: MacOS :: MacOS X
Classifier: Operating System :: Microsoft :: Windows
Classifier: Operating System :: POSIX :: Linux
Classifier: Programming Language :: Python :: 3.12
Requires-Python: >=3.12
Requires-Dist: dftt-timecode
Requires-Dist: multimethod
Requires-Dist: psutil
Provides-Extra: docs
Requires-Dist: alabaster; extra == 'docs'
Requires-Dist: pydata-sphinx-theme; extra == 'docs'
Requires-Dist: sphinx; extra == 'docs'
Requires-Dist: sphinxcontrib-applehelp==1.0.4; extra == 'docs'
Requires-Dist: sphinxcontrib-devhelp==1.0.2; extra == 'docs'
Requires-Dist: sphinxcontrib-htmlhelp==2.0.1; extra == 'docs'
Requires-Dist: sphinxcontrib-jsmath==1.0.1; extra == 'docs'
Requires-Dist: sphinxcontrib-qthelp==1.0.3; extra == 'docs'
Requires-Dist: sphinxcontrib-serializinghtml==1.1.10; extra == 'docs'
